afronomy/__init__.py
afronomy/apps/__init__.py
afronomy/apps/hello.py
afronomy/apps/main.py
afronomy/cabs/hello.yml
afronomy/parser/__init__.py
afronomy/tests/__init__.py
afronomy/tests/test_hello.py
afronomy-0.0.1rc1.dist-info/LICENSE
afronomy-0.0.1rc1.dist-info/METADATA
afronomy-0.0.1rc1.dist-info/WHEEL
afronomy-0.0.1rc1.dist-info/entry_points.txt
afronomy-0.0.1rc1.dist-info/RECORD
