Metadata-Version: 2.1
Name: afronomy
Version: 0.0.1rc1
Summary: Application to simulate self-calibration and quality assurance checks
Home-page: https://github.com/athanaseus/afronomy
License: MIT
Keywords: Astronomy,Masking,Imaging
Author: Athanaseus Ramaila & RATT
Author-email: ramaila.jat@gmail.com
Requires-Python: >=3.10,<4.0
Classifier: Development Status :: 4 - Beta
Classifier: Intended Audience :: Science/Research
Classifier: License :: OSI Approved :: MIT License
Classifier: Operating System :: POSIX :: Linux
Classifier: Programming Language :: Python
Classifier: Programming Language :: Python :: 3
Classifier: Programming Language :: Python :: 3.10
Classifier: Programming Language :: Python :: 3.11
Classifier: Programming Language :: Python :: 3.12
Classifier: Programming Language :: Python :: 3.13
Classifier: Topic :: Scientific/Engineering :: Astronomy
Provides-Extra: testing
Requires-Dist: click (>=8.1,<9.0)
Requires-Dist: codex-africanus (==0.4)
Requires-Dist: flaky ; extra == "testing"
Requires-Dist: pytest ; extra == "testing"
Requires-Dist: pytest-flake8 ; extra == "testing"
Requires-Dist: stimela
Project-URL: Repository, https://github.com/athanseus/afronomy.git
